hyvis/__init__.py
hyvis/basic_scans.py
hyvis/dr_tools.py
hyvis/native_landscapes.py
hyvis/video_scans.py
hyvis-0.1.1.dist-info/LICENSE.txt
hyvis-0.1.1.dist-info/METADATA
hyvis-0.1.1.dist-info/WHEEL
hyvis-0.1.1.dist-info/top_level.txt
hyvis-0.1.1.dist-info/RECORD
