Metadata-Version: 2.2
Name: hyvis
Version: 0.1.1
Summary: A package for visualization of quantum-classical hybrid systems.
Author-email: Lucas Euler <lucas.euler@jos-quantum.de>
Requires-Python: >=3.10
License-File: LICENSE.txt
Requires-Dist: numpy>=1.26.4
Requires-Dist: scikit-learn>=1.4.2
Requires-Dist: matplotlib>=3.8.4
Provides-Extra: qaoa
Requires-Dist: qiskit>=1.1.1; extra == "qaoa"
Requires-Dist: qiskit-aer>=0.14.2; extra == "qaoa"
